<?xml version="1.0" encoding="utf-8" ?>
<LanguageData>

  <Autosaving>Salvare Automată</Autosaving>
  
  <GameStartDialog> Sirenele de urgență răsună pe nava mamă in timp ce nava pare că se destramă. 3 dintre persoanele de pe navă reușesc să ajungă la capsulele de evacuare înainte ca nava să fie distrusă.\n\nCeva timp mai târziu, aterizați pe o planetă îndepărtată.\n\nBucăți din fosta navă se prăbușesc în apropiere, trebuie să concepi un plan pentru supraviețuire.</GameStartDialog>

  <Colony>Colonie</Colony>
  
  <ChangeLanguageFromMainMenu>Limba se poate schimba doar din meniul principal.</ChangeLanguageFromMainMenu>

  <AndLower>și</AndLower>
  <DisabledLower>dezactivat</DisabledLower>

  <CloseButton>Închide</CloseButton>


  <VersionIndicator>Versiunea {0}</VersionIndicator>
  <DevelopmentBuildLower>versiune de dezvoltare</DevelopmentBuildLower>
  <CompiledOn>Compilat {0}</CompiledOn>



  <!-- Content generation-->
  
	<MeatLabel>Carne de {0}</MeatLabel>
  <MeatDesc>Carne crudă de {0}.</MeatDesc>

  <LeatherLabel>Piele de {0}</LeatherLabel>
  <LeatherDesc>Piele de {0}.</LeatherDesc>

  <CorpseLabel>Cadavru de {0} </CorpseLabel>
	<CorpseDesc>Cadavru de{0}.</CorpseDesc>
  <DeadLabel>{0} (mort)</DeadLabel>

  <RoughStoneTerrainLabel>{0} rugos</RoughStoneTerrainLabel>
  <RoughStoneTerrainDesc>Sol {0} natural, rugos.</RoughStoneTerrainDesc>
  <RoughHewnStoneTerrainLabel>{0} rugos</RoughHewnStoneTerrainLabel>
  <RoughHewnStoneTerrainDesc>Podea de {0} șlefuit imperfect.</RoughHewnStoneTerrainDesc>
  <SmoothStoneTerrainLabel>{0} șlefuită</SmoothStoneTerrainLabel>
  <SmoothStoneTerrainDesc>Podea de {0} natural, șlefuit.</SmoothStoneTerrainDesc>

  <BlueprintLabelExtra> (schemă)</BlueprintLabelExtra>
  <FrameLabelExtra> (construcție)</FrameLabelExtra>


  <!-- For things made of stuff, e.g. "Stone bed" -->
  <!-- 0 is the stuffAdjective property under stuffProps and 1 is the label -->
  <ThingMadeOfStuffLabel>{0} {1}</ThingMadeOfStuffLabel>

  <VariousLabel>(variat)</VariousLabel>

  <!-- History events -->
  <ColonistDied>Colonist decedat</ColonistDied>
  
  
  
</LanguageData>
