<?xml version="1.0" encoding="utf-8"?>
<LanguageData>

  <RecruitPrisonerChance.label>probabilitate de recrutare priyonier</RecruitPrisonerChance.label>
  <RecruitPrisonerChance.description>Probabilitate ca aceasta persoană să recruteze un prizonier.</RecruitPrisonerChance.description>

  <TameAnimalChance.label>probabilitate de îmblânzire animal</TameAnimalChance.label>
  <TameAnimalChance.description>Probabilitatea ca această persoană sa îmblânzească un animal..</TameAnimalChance.description>

  <TrainAnimalChance.label>probabilitate de dresare animal</TrainAnimalChance.label>
  <TrainAnimalChance.description>Probabilitate ca această persoana să dreseze un animal intro incercare.Se poate modifica in funcţie de animal.</TrainAnimalChance.description>

  <SocialImpact.label>impact social</SocialImpact.label>
  <SocialImpact.description>Când această persoană interacţionează,impactul asupra celeilalte persoane.</SocialImpact.description>

  <GiftImpact.label>impactul cadoului diplomatic</GiftImpact.label>
  <GiftImpact.description>Când această persoană oferă un cadou altei facţiuni ,impactul acestuia asupra relaţiei dintre ele.</GiftImpact.description>

  <TradePriceImprovement.label>imbunătaţirea preţurilor de comerţ</TradePriceImprovement.label>
  <TradePriceImprovement.description>Când această persoana negociază preţurile de vânzare-cumpărare ,sunt modificate de acest procent.</TradePriceImprovement.description>


</LanguageData>