<?xml version="1.0" encoding="utf-8"?>
<LanguageData>

  <!-- SPECIAL: Floors from natural stones -->

  <Sandstone_Rough.label>gresie aspră</Sandstone_Rough.label>
  <Sandstone_RoughHewn.label>gresie necioplită</Sandstone_RoughHewn.label>
  <Sandstone_Smooth.label>gresie netedă</Sandstone_Smooth.label>

  <Granite_Rough.label>granit dur</Granite_Rough.label>
  <Granite_RoughHewn.label>granit necioplit</Granite_RoughHewn.label>
  <Granite_Smooth.label>granit neted</Granite_Smooth.label>

  <Limestone_Rough.label>calcar dur</Limestone_Rough.label>
  <Limestone_RoughHewn.label>calcar necioplit</Limestone_RoughHewn.label>
  <Limestone_Smooth.label>calcar neted</Limestone_Smooth.label>

  <Slate_Rough.label>ardezie aspră</Slate_Rough.label>
  <Slate_RoughHewn.label>ardezie necioplită</Slate_RoughHewn.label>
  <Slate_Smooth.label>smooth slate</Slate_Smooth.label>

  <Marble_Rough.label>marmură aspră</Marble_Rough.label>
  <Marble_RoughHewn.label>marmură necioplită</Marble_RoughHewn.label>
  <Marble_Smooth.label>marmură netedă</Marble_Smooth.label>


</LanguageData>