<?xml version="1.0" encoding="UTF-8"?>
<LanguageData>

  <!-- Main menu -->
  <!-- EN: Tutorial -->
  <Tutorial>TODO</Tutorial>
  <!-- EN: New colony -->
  <NewColony>Colonie nouă</NewColony>
  <!-- EN: Back to game -->
  <BackToGame>Continuare joc</BackToGame>
  <!-- EN: Review scenario -->
  <ReviewScenario>TODO</ReviewScenario>
  <!-- EN: Save -->
  <Save>Salvare colonie</Save>
  <!-- EN: Load game -->
  <LoadGame>TODO</LoadGame>
  <!-- EN: Options -->
  <Options>Setări</Options>
  <!-- EN: Mod -->
  <Mod>TODO</Mod>
  <!-- EN: Mods -->
  <Mods>Îmbunătățiri</Mods>
  <!-- EN: Save translation report -->
  <SaveTranslationReport>TODO</SaveTranslationReport>
  <!-- EN: Generating translation report -->
  <GeneratingTranslationReport>TODO</GeneratingTranslationReport>
  <!-- EN: Cleanup translation files -->
  <CleanupTranslationFiles>TODO</CleanupTranslationFiles>
  <!-- EN: Update translations files (TKey's) -->
  <TranslationFilesTKeyUpdate>TODO</TranslationFilesTKeyUpdate>
  <!-- EN: Cleaning translation files -->
  <CleaningTranslationFiles>TODO</CleaningTranslationFiles>
  <!-- EN: Credits -->
  <Credits>Credite</Credits>
  <!-- EN: Quit to main menu -->
  <QuitToMainMenu>Întoarcere la meniul jocului</QuitToMainMenu>
  <!-- EN: Save and quit to menu -->
  <SaveAndQuitToMainMenu>TODO</SaveAndQuitToMainMenu>
  <!-- EN: Quit to OS -->
  <QuitToOS>Închide joc</QuitToOS>
  <!-- EN: Save and quit to OS -->
  <SaveAndQuitToOS>TODO</SaveAndQuitToOS>
  <!-- EN: Fiction primer -->
  <FictionPrimer>Fiction primer</FictionPrimer>
  <!-- EN: Ludeon blog -->
  <LudeonBlog>Blog-ul Ludeon</LudeonBlog>
  <!-- EN: Forums -->
  <Forums>Forum</Forums>
  <!-- EN: Official wiki -->
  <OfficialWiki>Wiki oficial</OfficialWiki>
  <!-- EN: Tynan's twitter -->
  <TynansTwitter>Pagina de twitter a lui Tynan</TynansTwitter>
  <!-- EN: Tynan's design book -->
  <TynansDesignBook>Cartea de design a lui Tynan</TynansDesignBook>
  <!-- EN: Help translate RimWorld -->
  <HelpTranslate>Participă la traducerea jocului!</HelpTranslate>
  <!-- EN: Buy soundtrack -->
  <BuySoundtrack>TODO</BuySoundtrack>
  <!-- EN: Create world -->
  <CreateWorld>Creare lume</CreateWorld>

  <!-- Main menu translations info window -->
  <!-- EN: All translations of RimWorld are fan-made. This fan-made translation was created by the following excellent volunteers:\n\n{0} -->
  <TranslationThanks>TODO</TranslationThanks>
  <!-- EN: You can contribute too. Click below to learn more (opens web browser). -->
  <TranslationHowToContribute>TODO</TranslationHowToContribute>
  <!-- EN: Learn more -->
  <LearnMore>TODO</LearnMore>

  <!-- Main menu dev build -->
  <!-- EN: Warning: This is an unstable development build. This means we are running design experiments and doing technical development.\n\nSome things will be temporarily unbalanced on purpose. This is a classic game design method where we deliberately go too far with a balance change in order to better understand balance boundaries. We can then use that information to decide on the final balance points.\n\nThere will also be bugs, including game-breaking ones. Save compatibility may break any time.\n\nIf you're okay with all of this, thanks for testing! If you don't want to be subject to our experiments, please play the latest stable version. -->
  <DevBuildWarning>TODO</DevBuildWarning>

  <!-- Create/review world -->
  <!-- EN: Review world -->
  <ReviewWorld>Vizualizare lume</ReviewWorld>
  <!-- EN: Generate -->
  <WorldGenerate>Generează lume</WorldGenerate>
  <!-- EN: Save and finish -->
  <WorldSaveAndFinish>Salvează si finalizează</WorldSaveAndFinish>
  <!-- EN: Reset -->
  <Reset>Resetare</Reset>
  <!-- EN: Globe coverage -->
  <PlanetCoverage>TODO</PlanetCoverage>
  <!-- EN: Overall rainfall -->
  <PlanetRainfall>TODO</PlanetRainfall>
  <!-- EN: Overall temperature -->
  <PlanetTemperature>TODO</PlanetTemperature>
  <!-- EN: Population -->
  <PlanetPopulation>TODO</PlanetPopulation>
  <!-- EN: Low -->
  <PlanetRainfall_Low>TODO</PlanetRainfall_Low>
  <!-- EN: Normal -->
  <PlanetRainfall_Normal>TODO</PlanetRainfall_Normal>
  <!-- EN: High -->
  <PlanetRainfall_High>TODO</PlanetRainfall_High>
  <!-- EN: Low -->
  <PlanetTemperature_Low>TODO</PlanetTemperature_Low>
  <!-- EN: Normal -->
  <PlanetTemperature_Normal>TODO</PlanetTemperature_Normal>
  <!-- EN: High -->
  <PlanetTemperature_High>TODO</PlanetTemperature_High>
  <!-- EN: Sparse -->
  <PlanetPopulation_Low>TODO</PlanetPopulation_Low>
  <!-- EN: Normal -->
  <PlanetPopulation_Normal>TODO</PlanetPopulation_Normal>
  <!-- EN: Crowded -->
  <PlanetPopulation_High>TODO</PlanetPopulation_High>
  <!-- EN: Seed -->
  <WorldSeed>Cod de generare</WorldSeed>
  <!-- EN: Randomize seed -->
  <RandomizeSeed>Generare cod aleator</RandomizeSeed>
  <!-- EN: The planet is always the same diameter, but since it’s far larger than needed for play, we don’t generate the whole surface because it can take a very long time. This is the percentage of the surface that you want generated. -->
  <PlanetCoverageTip>TODO</PlanetCoverageTip>
  <!-- EN: Factions -->
  <WorldFactionsTab>TODO</WorldFactionsTab>

  <!-- Select world -->
  <!-- EN: Select world -->
  <SelectWorld>Selectare lume</SelectWorld>
  <!-- EN: Select -->
  <WorldChooseButton>Selectează</WorldChooseButton>
  <!-- EN: No world files found. Create a world first. -->
  <NoWorldsFilesFound>Nu există nici o lume creată. Creează o lume nouă mai întâi.</NoWorldsFilesFound>
  
  <!-- Version info -->
  <!-- EN: Version {0} is now available. Check ludeon.com for more info. -->
  <BuildNowAvailable>Versiunea {0} este finalizată. Accesează www.ludeon.com pentru mai multe informații.</BuildNowAvailable>
  <!-- EN: This is the latest version. -->
  <BuildUpToDate>Aceasta este cea mai nouă versiune.</BuildUpToDate>
  <!-- EN: Error getting version info: {0} -->
  <ErrorGettingVersionInfo>Eroare în determinarea versiunii jocului: {0}</ErrorGettingVersionInfo>
  <!-- EN: Loading version info... -->
  <LoadingVersionInfo>Informații versiune prezentă</LoadingVersionInfo>

  <!-- World generator -->
  <!-- EN: Generate world -->
  <GenerateWorld>Generează lume</GenerateWorld>

  <!-- Mods config -->
  <!-- EN: Open Steam Workshop -->
  <OpenSteamWorkshop>TODO</OpenSteamWorkshop>
  <!-- EN: Get mods from forum -->
  <GetModsFromForum>TODO</GetModsFromForum>
  <!-- EN: Open mods data folder -->
  <OpenModsDataFolder>Deschide fișierul cu îmbunătățiri</OpenModsDataFolder>
  <!-- EN: Show mods data location -->
  <ShowModsDataLocation>TODO</ShowModsDataLocation>
  <!-- EN: Are you sure you want to disable the core mod? The game won't work at all unless you have another mod that replaces all the core functionality.\n\nRemember, other mods can override defs in the core mod by using the same defName. -->
  <ConfirmDisableCoreMod>Ești sigur că vrei sa dezactivezi nucleul de bază? Jocul nu va mai funcționa deloc dacă nu există un alt mod care să înlocuiască toate funcțiile de nucleului.\n\nReține, alte mod-uri pot suprapune defs-uri in mod-ul de bază dacă folosesc același defName.</ConfirmDisableCoreMod>
  <!-- EN: Are you sure you want to delete all the content for {0}? -->
  <ConfirmDeleteMod>TODO</ConfirmDeleteMod>
  <!-- EN: Auto-sort mods -->
  <ResolveModOrder>TODO</ResolveModOrder>
  <!-- EN: Unsubscribe -->
  <Unsubscribe>TODO</Unsubscribe>
  <!-- EN: Are you sure you want to unsubscribe from {0}? -->
  <ConfirmUnsubscribe>TODO</ConfirmUnsubscribe>
  <!-- EN: Author -->
  <Author>Autor</Author>
  <!-- EN: Workshop page -->
  <WorkshopPage>TODO</WorkshopPage>
  <!-- EN: Upload to Steam Workshop -->
  <UploadToSteamWorkshop>TODO</UploadToSteamWorkshop>
  <!-- EN: Update on Steam Workshop -->
  <UpdateOnSteamWorkshop>TODO</UpdateOnSteamWorkshop>
  <!-- EN: Upload already in progress. -->
  <UploadAlreadyInProgress>TODO</UploadAlreadyInProgress>
  <!-- EN: Workshop submission failed.\n\nReason: {0} -->
  <WorkshopSubmissionFailed>TODO</WorkshopSubmissionFailed>
  <!-- EN: Successfully uploaded {0}. -->
  <WorkshopUploadSucceeded>TODO</WorkshopUploadSucceeded>
  <!-- EN: Downloading -->
  <Downloading>TODO</Downloading>
  <!-- EN: Display fulfilled requirements -->
  <ModDisplayFulfilledRequirements>TODO</ModDisplayFulfilledRequirements>
  <!-- EN: Click to select. -->
  <ModClickToSelect>TODO</ModClickToSelect>
  <!-- EN: Click to go to website. -->
  <ModClickToGoToWebsite>TODO</ModClickToGoToWebsite>
  <!-- EN: Source -->
  <Source>TODO</Source>
  <!-- EN: For game version(s) -->
  <ModTargetVersion>TODO</ModTargetVersion>
  <!-- EN: ID -->
  <ModPackageId>TODO</ModPackageId>
  <!-- EN: This must be loaded before: {0}. -->
  <ModMustLoadBefore>TODO</ModMustLoadBefore>
  <!-- EN: This must be loaded after: {0}. -->
  <ModMustLoadAfter>TODO</ModMustLoadAfter>
  <!-- EN: Depends on: {0} -->
  <ModDependsOn>TODO</ModDependsOn>
  <!-- EN: Incompatible with: {0} -->
  <ModIncompatibleWith>TODO</ModIncompatibleWith>
  <!-- EN: This mod is incompatible with: {0}. -->
  <ModIncompatibleWithTip>TODO</ModIncompatibleWithTip>
  <!-- EN: This mod is loading in the wrong order relative to another mod. Use the 'auto-sort' button, or re-order the mods manually. -->
  <ModOrderingWarning>TODO</ModOrderingWarning>
  <!-- EN: Another active mod uses the same ID: {0}. -->
  <ModWithSameIdAlreadyActive>TODO</ModWithSameIdAlreadyActive>
  <!-- EN: There is a cyclic mod dependency starting with {0}. -->
  <ModCyclicDependency>TODO</ModCyclicDependency>
  <!-- EN: This requires following mods to work: {0}. -->
  <ModUnsatisfiedDependency>TODO</ModUnsatisfiedDependency>
  <!-- EN: This mod was not made for this version of RimWorld, and will probably not work correctly. -->
  <ModNotMadeForThisVersion>TODO</ModNotMadeForThisVersion>
  <!-- EN: This mod was made for a newer version of RimWorld than this, and will probably not work correctly. -->
  <ModNotMadeForThisVersion_Newer>TODO</ModNotMadeForThisVersion_Newer>
  <!-- EN: Mod needs properly formatted supported version information in About.xml. Like this: <supportedVersions><li>{0}</li></supportedVersions> - <targetVersion> is deprecated. Check log for further information. -->
  <MessageModNeedsWellFormattedTargetVersion>TODO</MessageModNeedsWellFormattedTargetVersion>
  <!-- EN: Mod needs a unique, properly formatted packageId in About.xml. It must must meet following requirements:\n\n  - Alphanumeric characters and dot only.\n  - No spaces.\n  - At least one dot.\n  - No repeated dots in a row, or starting or ending with a dot.\n  - 60 characters or less.\n  - Cannot contain word "Ludeon".\n\nFor example:\n<packageId>AuthorName.ModName</packageId>\n<packageId>AuthorName.ModName.Specific</packageId> -->
  <MessageModNeedsWellFormattedPackageId>TODO</MessageModNeedsWellFormattedPackageId>
  <!-- EN: This mod has issues in LoadFolders.xml, that you need to resolve before uploading: -->
  <ModHadLoadFolderIssues>TODO</ModHadLoadFolderIssues>
  <!-- EN: Folder {0} specified for version {1} doesn't exist. -->
  <ModLoadFolderDoesntExist>TODO</ModLoadFolderDoesntExist>
  <!-- EN: Malformed version string '{0}'. Correct format is Major.Minor (e.g. 1.1) -->
  <ModLoadFolderMalformedVersion>TODO</ModLoadFolderMalformedVersion>
  <!-- EN: The list of load folders for version {0} is empty. -->
  <ModLoadFolderListEmpty>TODO</ModLoadFolderListEmpty>
  <!-- EN: Version {0} lists the same folder more than once: {1}. -->
  <ModLoadFolderRepeatingFolder>TODO</ModLoadFolderRepeatingFolder>
  <!-- EN: Invalid version order: {0} should come before {1}. -->
  <ModLoadFolderOutOfOrder>TODO</ModLoadFolderOutOfOrder>
  <!-- EN: Invalid version order: 'default' should be defined first. -->
  <ModLoadFolderOutOfOrderDefault>TODO</ModLoadFolderOutOfOrderDefault>
  <!-- EN: Version {0} is defined in load folders, but is not listed in 'supportedVersions' of mod's About.xml. -->
  <ModLoadFolderDefinesUnsupportedGameVersion>TODO</ModLoadFolderDefinesUnsupportedGameVersion>
  <!-- EN: Drag to reorder -->
  <DragToReorder>TODO</DragToReorder>

  <!-- Select scenario -->
  <!-- EN: Choose scenario -->
  <ChooseScenario>TODO</ChooseScenario>
  <!-- EN: Custom -->
  <ScenariosCustom>TODO</ScenariosCustom>
  <!-- EN: Steam Workshop -->
  <ScenariosSteamWorkshop>TODO</ScenariosSteamWorkshop>
  <!-- EN: Scenario editor -->
  <ScenarioEditor>TODO</ScenarioEditor>
  <!-- EN: Delete -->
  <Delete>TODO</Delete>
  
  <!-- Scenario editor -->
  <!-- EN: seed -->
  <Seed>TODO</Seed>
  <!-- EN: Load -->
  <Load>Încărcare colonie precedentă</Load>
  <!-- EN: edit mode -->
  <EditMode>TODO</EditMode>
  <!-- EN: Summary -->
  <Summary>TODO</Summary>
  <!-- EN: Add part -->
  <AddPart>TODO</AddPart>
  <!-- EN: All text fields must be filled. -->
  <TextFieldsMustBeFilled>TODO</TextFieldsMustBeFilled>
  <!-- EN: Are you sure you want to upload this to the Steam Workshop?\n\nYou must agree to the Steam Workshop terms of service. Find the full terms here:\n\nhttp://steamcommunity.com/sharedfiles/workshoplegalagreement -->
  <ConfirmSteamWorkshopUpload>TODO</ConfirmSteamWorkshopUpload>
  <!-- EN: Obviously you should only upload content that you created yourself.\n\nDid you create this content yourself? -->
  <ConfirmContentAuthor>TODO</ConfirmContentAuthor>
  <!-- EN: Incompatible -->
  <Incompatible>TODO</Incompatible>
  <!-- EN: Too many (max {0}):  -->
  <TooMany>TODO</TooMany>
  <!-- EN: Can be updated on Workshop, since you are the author. -->
  <CanBeUpdatedOnWorkshop>TODO</CanBeUpdatedOnWorkshop>
  
  <!-- Select storyteller -->
  <!-- EN: Choose AI Storyteller -->
  <ChooseAIStoryteller>Alege un AI povestitor</ChooseAIStoryteller>
  <!-- EN: The AI Storyteller creates events like pirate raids, resource drops, or animal attacks. Their choices will affect the story of your colony. You can change these settings at any time. -->
  <HowStorytellersWork>AI-ul povestitor generează evenimente ca atacuri ale piraților, ale animalelor sau aterizări de resurse. Aceste alegeri vor afecta povestea coloniei tale.</HowStorytellersWork>
  <!-- EN: Please choose a difficulty setting. -->
  <MustChooseDifficulty>TODO</MustChooseDifficulty>
  <!-- EN: Difficulty -->
  <Difficulty>TODO</Difficulty>
  <!-- EN: Commitment mode -->
  <CommitmentMode>TODO</CommitmentMode>
  <!-- EN: Reload anytime mode -->
  <ReloadAnytimeMode>TODO</ReloadAnytimeMode>
  <!-- EN: Please choose commitment mode or reload anytime mode. -->
  <MustChoosePermadeath>TODO</MustChoosePermadeath>
  <!-- EN: You can save and load the game at any time.\n\nThis is a good choice if you're still learning the game, if it fits your personal playstyle, if you're using mods that may break your game, or if you intend to self-enforce commitment mode. -->
  <ReloadAnytimeModeInfo>TODO</ReloadAnytimeModeInfo>
  <!-- EN: You can only save when quitting the game.\n\nSince RimWorld is a story generator, even losing all but one person is not the end of the game - it's part of the story. The game is designed to allow recovery after losses.\n\nPlaying out these terrible situations makes a story with both tragedy and triumph. It's the way RimWorld was designed to be played.\n\nThere's a reason Luke Skywalker didn't quit and reload when his family got killed - loss and recovery is dramatic. -->
  <PermadeathModeInfo>TODO</PermadeathModeInfo>
  <!-- EN: Storyteller and difficulty can be changed any time. -->
  <CanChangeStorytellerSettingsDuringPlay>TODO</CanChangeStorytellerSettingsDuringPlay>
  <!-- EN: Merciless mode -->
  <UnlockExtremeDifficulty>TODO</UnlockExtremeDifficulty>
  <!-- EN: Merciless mode is a special game mode where every challenge is turned up to extreme levels.\n\nMerciless mode unlocks automatically when you reach specific milestones. However, you can unlock it now.\n\nThis option is only recommended once you've played a high-difficulty game or two and want to have a good chance at dying despite your best efforts. -->
  <ConfirmUnlockExtremeDifficulty>TODO</ConfirmUnlockExtremeDifficulty>

  <!-- Site select -->
  <!-- EN: Select starting site -->
  <SelectStartingSite>TODO</SelectStartingSite>
  <!-- EN: Select random site -->
  <SelectRandomSite>TODO</SelectRandomSite>
  <!-- EN: Select site -->
  <SelectSite>Alege regiunea</SelectSite>
  <!-- EN: Please select a site. -->
  <MustSelectStartingSite>TODO</MustSelectStartingSite>
  <!-- EN: You cannot land on this biome: {0} -->
  <CannotLandBiome>Nu poți ateriza în acest mediu: {0}</CannotLandBiome>
  <!-- EN: Biome not implemented -->
  <BiomeNotImplemented>Mediul geografic nu este implementat</BiomeNotImplemented>
  <!-- EN: You cannot land on impassable mountains. -->
  <CannotLandImpassableMountains>TODO</CannotLandImpassableMountains>
  <!-- EN: {0} already have a base there. -->
  <BaseAlreadyThere>{0} au deja o colonie acolo.</BaseAlreadyThere>
  <!-- EN: You already have a base there. -->
  <YourBaseAlreadyThere>TODO</YourBaseAlreadyThere>
  <!-- EN: This tile is occupied. -->
  <TileOccupied>TODO</TileOccupied>
  <!-- EN: Settlements cannot be directly adjacent to each other. -->
  <FactionBaseAdjacent>TODO</FactionBaseAdjacent>
  <!-- EN: Biome -->
  <Biome>Mediu</Biome>
  <!-- EN: Terrain -->
  <Terrain>Relief</Terrain>
  <!-- EN: Road -->
  <Road>TODO</Road>
  <!-- EN: River -->
  <River>TODO</River>
  <!-- EN: Elevation -->
  <Elevation>Altitudine</Elevation>
  <!-- EN: Fertility -->
  <Fertility>Fertilitate</Fertility>
  <!-- EN: Average temperature -->
  <AvgTemp>Temperatură medie</AvgTemp>
  <!-- EN: Rainfall -->
  <Rainfall>Precipitații</Rainfall>
  <!-- EN: Special features -->
  <SpecialFeatures>TODO</SpecialFeatures>
  <!-- EN: northern coast -->
  <HasCoast0>Coasta Nordică</HasCoast0>
  <!-- EN: eastern coast -->
  <HasCoast1>Coasta Estică</HasCoast1>
  <!-- EN: southern coast -->
  <HasCoast2>Coasta Sudică</HasCoast2>
  <!-- EN: western coast -->
  <HasCoast3>Coasta Vestică</HasCoast3>
  <!-- EN: caves -->
  <HasCaves>TODO</HasCaves>
  <!-- EN: Faction base -->
  <FactionBase>Capitala unei facțiuni</FactionBase>
  <!-- EN: Stone types -->
  <StoneTypesHere>Tipuri de roci</StoneTypesHere>
  <!-- EN: Time zone -->
  <TimeZone>TODO</TimeZone>
  <!-- EN: Movement difficulty -->
  <MovementDifficulty>TODO</MovementDifficulty>
  <!-- EN: Animals can graze now -->
  <AnimalsCanGrazeNow>TODO</AnimalsCanGrazeNow>
  <!-- EN: Average disease frequency -->
  <AverageDiseaseFrequency>TODO</AverageDiseaseFrequency>
  <!-- EN: per year -->
  <PerYear>TODO</PerYear>
  <!-- EN: Forageability -->
  <Forageability>TODO</Forageability>
  <!-- EN: None of the selected people can do the following jobs:\n\n{0}\n\nThis can make the game more difficult than usual. Are you sure you want to continue? -->
  <ConfirmRequiredWorkTypeDisabledForEveryone>TODO</ConfirmRequiredWorkTypeDisabledForEveryone>

  <!-- Character chooser -->
  <!-- EN: Create characters -->
  <CreateCharacters>Creează personaje</CreateCharacters>
  <!-- EN: The character's first name.\n\nThis is only displayed in certain menus. -->
  <FirstNameDesc>Prenumele personajului.\n\nAcesta este afișat doar în anumite meniuri.</FirstNameDesc>
  <!-- EN: The character's short identifier.\n\nThis is displayed at all times. It can be the first or last name, or a completely separate nickname. -->
  <ShortIdentifierDesc>Porecla personajului.\n\nAceasta este afișată mereu. Poate fi numele, prenumele sau cu totul altceva.</ShortIdentifierDesc>
  <!-- EN: The character's last name.\n\nThis is only displayed in certain menus. -->
  <LastNameDesc>Numele personajului.\n\nAcesta este afișat doar în anumite meniuri.</LastNameDesc>
  <!-- EN: Randomize -->
  <Randomize>Alege aleator</Randomize>
  <!-- EN: age {0} -->
  <AgeIndicator>vârstă {0}</AgeIndicator>
  <!-- EN: {PAWN_race}, age {PAWN_ageFull} -->
  <PawnSummary>TODO</PawnSummary>
  <!-- EN: {PAWN_gender} {PAWN_race}, age {PAWN_ageFull} -->
  <PawnSummaryWithGender>TODO</PawnSummaryWithGender>
  <!-- EN: Backstory -->
  <Backstory>Poveste</Backstory>
  <!-- EN: Incapable of -->
  <IncapableOf>Incapabil de</IncapableOf>
  <!-- EN: Abilities -->
  <Abilities>TODO</Abilities>
  <!-- EN: Caused by backstory: {0} -->
  <IncapableOfTooltipBackstory>TODO</IncapableOfTooltipBackstory>
  <!-- EN: Caused by title: {0} -->
  <IncapableOfTooltipTitle>TODO</IncapableOfTooltipTitle>
  <!-- EN: Caused by trait: {0} -->
  <IncapableOfTooltipTrait>TODO</IncapableOfTooltipTrait>
  <!-- EN: Caused by: {0} -->
  <IncapableOfTooltipHediff>TODO</IncapableOfTooltipHediff>
  <!-- EN: Disabled work types: -->
  <IncapableOfTooltipWorkTypes>TODO</IncapableOfTooltipWorkTypes>
  <!-- EN: Caused by quest status: {0} -->
  <IncapableOfTooltipQuest>TODO</IncapableOfTooltipQuest>
  <!-- EN: Traits -->
  <Traits>Trăsături</Traits>
  <!-- EN: Permanent mood effect -->
  <PermanentMoodEffect>Efect permament asupra dispoziției</PermanentMoodEffect>
  <!-- EN: Skills -->
  <Skills>Abilități</Skills>
  <!-- EN: none -->
  <NoneLower>Nimic</NoneLower>
  <!-- EN: Adulthood -->
  <Adulthood>Viață de adult</Adulthood>
  <!-- EN: Childhood -->
  <Childhood>Copilărie</Childhood>
  <!-- EN: Current -->
  <Current>TODO</Current>
  <!-- EN: male -->
  <Male>Mascul</Male>
  <!-- EN: female -->
  <Female>Femelă</Female>
  <!-- EN: male -->
  <MaleAnimal>TODO</MaleAnimal>
  <!-- EN: female -->
  <FemaleAnimal>TODO</FemaleAnimal>
  <!-- EN: Pain -->
  <Pain>Durere</Pain>
  <!-- EN: Health -->
  <Health>Sănătate</Health>
  <!-- EN: Relations -->
  <Relations>TODO</Relations>
  <!-- EN: Team skills -->
  <TeamSkills>TODO</TeamSkills>
  <!-- EN: Selected -->
  <StartingPawnsSelected>TODO</StartingPawnsSelected>
  <!-- EN: Left behind -->
  <StartingPawnsLeftBehind>TODO</StartingPawnsLeftBehind>
  
  <!-- Misc -->
  <!-- EN: Start -->
  <Start>Start</Start>
  <!-- EN: Advanced -->
  <Advanced>Avansat</Advanced>
  <!-- EN: Next -->
  <Next>Înainte</Next>
  <!-- EN: Back -->
  <Back>Înapoi</Back>
  <!-- EN: Show Materials -->
  <ShowMaterials>TODO</ShowMaterials>
  <!-- EN: Gameplay -->
  <Gameplay>Mecanici de joc</Gameplay>
  <!-- EN: Really quit? You'll lose unsaved progress. -->
  <ConfirmQuit>Sigur vrei să închizi? Conținutul nesalvat va fi pierdut.</ConfirmQuit>
  <!-- EN: Each person needs a valid name. -->
  <EveryoneNeedsValidName>Fiecare persoană are nevoie de un nume valid.</EveryoneNeedsValidName>
  <!-- EN: None of the selected people can do the following jobs -->
  <RequiredWorkTypeDisabledForEveryone>TODO</RequiredWorkTypeDisabledForEveryone>
  <!-- EN: Quit -->
  <Quit>TODO</Quit>
  <!-- EN: Ignore -->
  <Ignore>TODO</Ignore>
  
  <!-- Progress bar -->
  <!-- EN: Generating world -->
  <GeneratingWorld>Generează lume...</GeneratingWorld>
  <!-- EN: Generating planet -->
  <GeneratingPlanet>TODO</GeneratingPlanet>
  <!-- EN: Generating map -->
  <GeneratingMap>Generează hartă...</GeneratingMap>
  <!-- EN: Generating map for new encounter -->
  <GeneratingMapForNewEncounter>TODO</GeneratingMapForNewEncounter>

  <!-- EN: Click for more info -->
  <ClickForMoreInfo>TODO</ClickForMoreInfo>
  <!-- EN: No more information is available. -->
  <NoMoreInfoAvailable>TODO</NoMoreInfoAvailable>

</LanguageData>